plenario_mailer_core/__init__.py
plenario_mailer_core/apps.py
plenario_mailer_core/defaults.py
plenario_mailer_core/mailer.py
plenario_mailer_core/models.py
plenario_mailer_core/tests.py
plenario_mailer_core/migrations/__init__.py
plenario_mailer_core/templates/plenario_mailer_core/base.j2
plenario_mailer_core/templates/plenario_mailer_core/data-set-approved.j2
plenario_mailer_core/templates/plenario_mailer_core/data-set-erred.j2
plenario_mailer_core/templates/plenario_mailer_core/data-set-fixed.j2
plenario_mailer_core/templates/plenario_mailer_core/data-set-ready.j2
plenario_mailer_core-0.0.2.dist-info/DESCRIPTION.rst
plenario_mailer_core-0.0.2.dist-info/METADATA
plenario_mailer_core-0.0.2.dist-info/RECORD
plenario_mailer_core-0.0.2.dist-info/WHEEL
plenario_mailer_core-0.0.2.dist-info/metadata.json
plenario_mailer_core-0.0.2.dist-info/top_level.txt
tests/app/__init__.py
tests/app/apps.py
tests/app/models.py
tests/app/migrations/0001_initial.py
tests/app/migrations/__init__.py
